{
  "alternatives": 7,
  "budget_agreement": true,
  "case_id": "explicit-p2-harmless-s102",
  "chebyshev": {
    "conservative_upper": "3/8",
    "failure_above_upper": null,
    "ratio": null,
    "strict_gap_at_test_rho": "8",
    "tie_at_upper": null,
    "upper": null
  },
  "classification_agreement": true,
  "domain_fraction_inspected": 0.0,
  "expected_class": "harmless",
  "explicit_budget": "0",
  "explicit_oracle_calls": 1,
  "explicit_status": "STRICTLY_CERTIFIED",
  "explicit_time_ns": 55063,
  "family": "explicit",
  "full_budget": "0",
  "full_status": "STRICTLY_CERTIFIED",
  "full_time_ns": 1195295,
  "grid_baseline": {},
  "instance_digest": "sha256:905e526267087e066631730d35f2504a64eef20b538accb0081bcd126db63aa8",
  "m": 1,
  "observed_class": "harmless",
  "p": 2,
  "protocol_sha256": "d7e0a1351722e8bc41a9ac64617b455bad30125c016ed52916c95804ba065aaa",
  "scale_invariant": true,
  "structured_budget": "0",
  "structured_margin": "13/24",
  "structured_oracle_calls": 1,
  "structured_rows": 0,
  "structured_status": "STRICTLY_CERTIFIED",
  "structured_time_ns": 73621
}
