{
  "case_id": "explicit-p3-repairable-s101",
  "family": "explicit_controlled",
  "instance_digest": "sha256:343f628dfae01cfa2cc4c3baaa48b734fa8992a6b39b5b730dd7ced3db569d03",
  "protocol_sha256": "d7e0a1351722e8bc41a9ac64617b455bad30125c016ed52916c95804ba065aaa",
  "result": {
    "budget": "0",
    "challenger_ids": [
      "core1",
      "core0",
      "core2"
    ],
    "master_certificate": {
      "active_rows": [
        0,
        1,
        2,
        7
      ],
      "equality_multipliers": [
        "-1/20"
      ],
      "inequality_multipliers": [
        "3/10",
        "7/20",
        "7/20",
        "1/4"
      ],
      "objective": "-1/20",
      "point": [
        "7/20",
        "3/10",
        "7/20",
        "0",
        "-1/20"
      ],
      "status": "OPTIMAL"
    },
    "oracle_calls": 4,
    "oracle_proofs": [
      {
        "challengers_checked": 7,
        "minimum": "-1/18",
        "type": "explicit_enumeration"
      },
      {
        "challengers_checked": 7,
        "minimum": "-1/7",
        "type": "explicit_enumeration"
      },
      {
        "challengers_checked": 7,
        "minimum": "-1/7",
        "type": "explicit_enumeration"
      },
      {
        "challengers_checked": 7,
        "minimum": "-1/20",
        "type": "explicit_enumeration"
      }
    ],
    "parameters": {
      "budget": "0",
      "multipliers": [
        "0"
      ],
      "weights": [
        "7/20",
        "3/10",
        "7/20"
      ]
    },
    "retained_rows": 3,
    "value": "-1/20"
  },
  "schema": "mmor-profile-record-1.0"
}
